csv-to-sbdl.py
pyproject.toml
sbdl.py
sbdl_server.py
setup.py
sbdl.egg-info/PKG-INFO
sbdl.egg-info/SOURCES.txt
sbdl.egg-info/dependency_links.txt
sbdl.egg-info/entry_points.txt
sbdl.egg-info/requires.txt
sbdl.egg-info/top_level.txt