Metadata-Version: 2.1
Name: sbdl
Version: 1.20.4
Summary: System Behaviour Description Language (Compiler)
Home-page: https://sbdl.dev
Author: Michael A. Hicks
Author-email: michael@mahicks.org
License: Proprietary
Requires-Python: >=3.6
